pybisol.cp39-win_amd64.pyd
pybisol-0.1.0.dist-info/LICENSE
pybisol-0.1.0.dist-info/METADATA
pybisol-0.1.0.dist-info/WHEEL
pybisol-0.1.0.dist-info/top_level.txt
pybisol-0.1.0.dist-info/RECORD
